fileextend/__init__.py
fileextend/file.py
fileextend/tar.py
fileextend-0.2.dist-info/METADATA
fileextend-0.2.dist-info/WHEEL
fileextend-0.2.dist-info/top_level.txt
fileextend-0.2.dist-info/RECORD
