Metadata-Version: 2.4
Name: fileextend
Version: 0.2
Summary: File extends
Author: Krzysztof Żyłka
Author-email: krzysztofzylka@yahoo.com
Requires-Dist: pathlib
Dynamic: author
Dynamic: author-email
Dynamic: description
Dynamic: description-content-type
Dynamic: requires-dist
Dynamic: summary
